ez_webdriver/__init__.py
ez_webdriver/ez_webdriver.py
ez_webdriver/.idea/workspace.xml
ez_webdriver-1.1.7.dist-info/METADATA
ez_webdriver-1.1.7.dist-info/WHEEL
ez_webdriver-1.1.7.dist-info/licenses/LICENSE
ez_webdriver-1.1.7.dist-info/RECORD
