Metadata-Version: 2.1
Name: ez-webdriver
Version: 1.1.7
Summary: 简单,快速的获取浏览器驱动,优先使用国内镜像,对标webdriver_manager模块(Quickly obtain the browser driver for China's Network Environment)
Project-URL: Homepage, https://github.com/wz-wong/ez-webdriver
Project-URL: Bug Tracker, https://github.com/wz-wong/ez-webdriver/issues
Author-email: wzzxx <wz_wong@qq.com>
License-File: LICENSE
Classifier: License :: OSI Approved :: MIT License
Classifier: Operating System :: OS Independent
Classifier: Programming Language :: Python :: 3
Requires-Python: >=3.6
